nem_py-0.0.7.data/scripts/nempy-cli.py
nempy/__init__.py
nempy/config.py
nempy/engine.py
nempy/ui.py
nempy/user_data.py
nempy/wallet.py
nempy/bin/nempy-cli.py
nempy/sym/__init__.py
nempy/sym/api.py
nempy/sym/config.py
nempy/sym/constants.py
nempy/sym/ed25519.py
nempy/sym/network.py
nempy/utils/__init__.py
nempy/utils/account.py
nempy/utils/measure_latency.py
nempy/utils/monitoring.py
nempy/utils/profile.py
nem_py-0.0.7.dist-info/LICENSE
nem_py-0.0.7.dist-info/METADATA
nem_py-0.0.7.dist-info/WHEEL
nem_py-0.0.7.dist-info/top_level.txt
nem_py-0.0.7.dist-info/RECORD
