Metadata-Version: 2.1
Name: nem-py
Version: 0.0.7
Summary: High-level wrapper for working with cryptocurrencies of the NEM ecosystem
Home-page: https://github.com/DENjjA/nempy
Author: Denys Shcheglov
Author-email: ikuzen@gmail.com
License: UNKNOWN
Project-URL: Bug Tracker, https://github.com/DENjjA/nempy/issues
Platform: UNKNOWN
Classifier: Programming Language :: Python :: 3
Classifier: License :: OSI Approved :: Apache Software License
Classifier: Operating System :: OS Independent
Requires-Python: >=3.6.0
License-File: LICENSE
Requires-Dist: bcrypt (==3.2.0)
Requires-Dist: bip-utils (==1.11.1)
Requires-Dist: blessed (==1.17.6)
Requires-Dist: catbuffer (==1.0.0)
Requires-Dist: certifi (==2021.5.30)
Requires-Dist: cffi (==1.14.6)
Requires-Dist: charset-normalizer (==2.0.4)
Requires-Dist: click (==7.1.2)
Requires-Dist: cryptography (==3.4.6)
Requires-Dist: ecdsa (==0.17.0)
Requires-Dist: idna (==3.2)
Requires-Dist: inquirer (==2.7.0)
Requires-Dist: mnemonic (==0.19)
Requires-Dist: nose (==1.3.7)
Requires-Dist: password-strength (==0.0.3.post2)
Requires-Dist: pillow (==8.1.1)
Requires-Dist: pycparser (==2.20)
Requires-Dist: pycryptodome (==3.10.1)
Requires-Dist: pycryptodomex (==3.10.1)
Requires-Dist: pydantic (==1.8.2)
Requires-Dist: pyfiglet (==0.7.6)
Requires-Dist: pysha3 (==1.0.2)
Requires-Dist: python-editor (==1.0.4)
Requires-Dist: pyyaml (==5.4.1)
Requires-Dist: pyzbar (==0.1.8)
Requires-Dist: qrcode (==6.1)
Requires-Dist: readchar (==2.0.1)
Requires-Dist: requests (==2.26.0)
Requires-Dist: six (==1.16.0)
Requires-Dist: stdiomask (==0.0.6)
Requires-Dist: symbol-sdk-core-python (==1.0.3)
Requires-Dist: tabulate (==0.8.9)
Requires-Dist: typing-extensions (==3.10.0.0)
Requires-Dist: urllib3 (==1.26.6)
Requires-Dist: wcwidth (==0.2.5)
Requires-Dist: websockets (==9.1)
